pydatav/__init__.py
pydatav/api/__init__.py
pydatav/api/flask_web.py
pydatav/api/image.py
pydatav/core/ExcelParser.py
pydatav/core/ImageProcess.py
pydatav/core/__init__.py
pydatav/lib/__init__.py
pydatav/lib/utils/__init__.py
pydatav/lib/utils/except_utils.py
pydatav/lib/utils/pandas_mem.py
pydatav/lib/utils/time_utils.py
tests/__init__.py
pydatav-0.0.2.dist-info/LICENSE
pydatav-0.0.2.dist-info/METADATA
pydatav-0.0.2.dist-info/WHEEL
pydatav-0.0.2.dist-info/top_level.txt
pydatav-0.0.2.dist-info/RECORD
