Metadata-Version: 2.1
Name: pydatav
Version: 0.0.2
Summary: python for data visualisation
Home-page: https://github.com/CoderWanFeng/pydatav
Author: CoderWanFeng
Author-email: 1957875073@qq.com
License: Apache-2.0 license
Project-URL: Bug Tracker, https://github.com/CoderWanFeng/pydatav/issues
Project-URL: Documentation, https://github.com/CoderWanFeng/pydatav/blob/master/README.md
Project-URL: Source Code, https://github.com/CoderWanFeng/pydatav
Platform: any
Requires-Python: >=3.8
License-File: LICENSE
Requires-Dist: wordcloud
Requires-Dist: jieba
